OpenImageIO/__init__.pyi
OpenImageIO/py.typed
PyOpenColorIO/__init__.pyi
PyOpenColorIO/py.typed
types_oiio_python-3.0.10.0.1.dist-info/licenses/LICENSE
types_oiio_python-3.0.10.0.1.dist-info/METADATA
types_oiio_python-3.0.10.0.1.dist-info/WHEEL
types_oiio_python-3.0.10.0.1.dist-info/top_level.txt
types_oiio_python-3.0.10.0.1.dist-info/RECORD
