Metadata-Version: 2.4
Name: types-oiio-python
Version: 3.0.10.0.1
Summary: Type stubs for oiio-python
Author: Paul Parneix
Project-URL: Homepage, https://github.com/pypoulp/types-oiio-python
Classifier: Intended Audience :: Developers
Classifier: Programming Language :: Python
Classifier: Programming Language :: Python :: 3
Classifier: Programming Language :: Python :: 3 :: Only
Classifier: Programming Language :: Python :: 3.8
Classifier: Programming Language :: Python :: 3.9
Classifier: Programming Language :: Python :: 3.10
Classifier: Programming Language :: Python :: 3.11
Classifier: Programming Language :: Python :: 3.12
Classifier: Programming Language :: Python :: 3.13
Classifier: Programming Language :: Python :: Implementation :: CPython
Requires-Python: >=3.8
License-File: LICENSE
Requires-Dist: typing-extensions
Provides-Extra: dev
Requires-Dist: mypy; extra == "dev"
Requires-Dist: isort; extra == "dev"
Requires-Dist: black; extra == "dev"
Requires-Dist: build; extra == "dev"
Requires-Dist: typing-extensions; extra == "dev"
Requires-Dist: oiio-python; extra == "dev"
Requires-Dist: stubgenlib; extra == "dev"
Dynamic: license-file
